LICENSE
README.md
pyproject.toml
setup.py
perftracker/__init__.py
perftracker/perftracker.py
perftracker.egg-info/PKG-INFO
perftracker.egg-info/SOURCES.txt
perftracker.egg-info/dependency_links.txt
perftracker.egg-info/top_level.txt
tests/test_perftracker.py