Metadata-Version: 2.1
Name: perftracker
Version: 1.4.0
Summary: PerfTracker is a lightweight function performance monitoring framework
Home-page: https://github.com/vertyco/perftracker
Author: vertyco
Author-email: alex.c.goble@gmail.com
Classifier: Development Status :: 4 - Beta
Classifier: Intended Audience :: Developers
Classifier: License :: OSI Approved :: MIT License
Classifier: Programming Language :: Python :: 3
Classifier: Programming Language :: Python :: 3.9
Classifier: Programming Language :: Python :: 3.10
Classifier: Programming Language :: Python :: 3.11
Classifier: Framework :: Pydantic :: 1
Classifier: Framework :: Pydantic :: 2
Classifier: Framework :: Pytest
Classifier: Operating System :: OS Independent
Classifier: Topic :: Utilities
Classifier: Typing :: Typed
Classifier: Natural Language :: English
Requires-Python: >=3.9
License-File: LICENSE
